tracextlinksnewwindow/__init__.py
tracextlinksnewwindow/plugin.py
tracextlinksnewwindow/htdocs/extlinks.js
TracExtLinksNewWindow-1.2.dist-info/METADATA
TracExtLinksNewWindow-1.2.dist-info/WHEEL
TracExtLinksNewWindow-1.2.dist-info/entry_points.txt
TracExtLinksNewWindow-1.2.dist-info/top_level.txt
TracExtLinksNewWindow-1.2.dist-info/RECORD
