Metadata-Version: 2.1
Name: TracExtLinksNewWindow
Version: 1.2
Summary: Trac plugin to open external links in a new window.
Home-page: https://trac-hacks.org/wiki/ExternalLinksNewWindow
Author: Martin Scharrer
Author-email: martin@scharrer-online.de
License: GPLv3
Download-URL: https://pypi.python.org/pypi/ExternalLinksNewWindowPlugin
Platform: UNKNOWN
Classifier: Framework :: Trac
Requires-Dist: Trac
